LICENSE
MANIFEST.in
README.rst
setup.py
geodb/__init__.py
geodb/admin.py
geodb/enumerations.py
geodb/geo_calc.py
geodb/geoapi.py
geodb/middleware.py
geodb/models.py
geodb/radarchart.py
geodb/router copy.py
geodb/router.py
geodb/tasks.py
geodb/tests.py
geodb/update_add_summary.py
geodb/urls.py
geodb/usgs_comcat.py
geodb/views.py
geodb/initialdata/afg_admbnda_int.dbf
geodb/initialdata/afg_admbnda_int.prj
geodb/initialdata/afg_admbnda_int.qpj
geodb/initialdata/afg_admbnda_int.shp
geodb/initialdata/afg_admbnda_int.shx
geodb/initialdata/water.dbf
geodb/initialdata/water.prj
geodb/initialdata/water.qpj
geodb/initialdata/water.shp
geodb/initialdata/water.shx
geodb/locale/prs/LC_MESSAGES/django.mo
geodb/locale/prs/LC_MESSAGES/django.po
geodb/locale/ps/LC_MESSAGES/django.mo
geodb/locale/ps/LC_MESSAGES/django.po
geodb/migrations/0001_initial.py
geodb/migrations/0001_initial.py_
geodb/migrations/0001_initial.pyc
geodb/migrations/0002_auto_20181128_1016.py
geodb/migrations/0002_auto_20181128_1016.pyc
geodb/migrations/__init__.py
geodb/migrations/__init__.pyc
geodb/migrations/userfunctions_create.sql
geodb/migrations/userfunctions_drop.sql
geodb/migrations/userfunctions_migration.py
geodb/migrations/userfunctions_migration.pyc
geodb/templates/climateinfo.html
geodb/templates/demographic.html
geodb/templates/generalInfo.html
geodb/templates/radar.html
geodb/templates/weatherinfo.html
isdc_geodb.egg-info/PKG-INFO
isdc_geodb.egg-info/SOURCES.txt
isdc_geodb.egg-info/dependency_links.txt
isdc_geodb.egg-info/top_level.txt